temp2temp/__init__.py
temp2temp/temperature.py
temp2temp-1.0.0.dist-info/DESCRIPTION.rst
temp2temp-1.0.0.dist-info/METADATA
temp2temp-1.0.0.dist-info/RECORD
temp2temp-1.0.0.dist-info/WHEEL
temp2temp-1.0.0.dist-info/metadata.json
temp2temp-1.0.0.dist-info/top_level.txt
