Metadata-Version: 2.0
Name: temp2temp
Version: 1.0.0
Summary: Temperature conversion between C/D/F/K/Ra/Re/N/Rø
Home-page: https://gitlab.com/renegadevi/temp2temp
Author: Philip Andersen
Author-email: philip.andersen@codeofmagi.net
License: MIT
Keywords: temp2temp,temperature,conversion,math,science
Platform: UNKNOWN
Classifier: Development Status :: 5 - Production/Stable
Classifier: Intended Audience :: Developers
Classifier: Intended Audience :: Science/Research
Classifier: Topic :: Software Development :: Libraries
Classifier: Topic :: Software Development :: Libraries :: Python Modules
Classifier: Topic :: Scientific/Engineering :: Mathematics
Classifier: License :: OSI Approved :: MIT License
Classifier: Programming Language :: Python :: 3.3
Classifier: Programming Language :: Python :: 3.4
Classifier: Programming Language :: Python :: 3.5
Classifier: Programming Language :: Python :: 3.6
Classifier: Operating System :: OS Independent
Requires-Python: >=3
